[
  {
    "pk": 1,
    "model": "auth.user",
    "fields": {
      "groups": [],
      "password": "pbkdf2_sha256$20000$UCKeEVQQeSWH$ScpNo5e/EkMCHaFQwZR5OGDylJxwL1UsSV3cmYUzNOM=",
      "first_name": "",
      "is_active": true,
      "is_staff": false,
      "is_superuser": false,
      "last_login": "2015-11-29T08:58:42.506Z",
      "user_permissions": [],
      "last_name": "",
      "date_joined": "2015-11-29T08:57:57.407Z",
      "username": "registered",
      "email": "registered@example.com"
    }
  },
  {
    "pk": 2,
    "model": "auth.user",
    "fields": {
      "groups": [],
      "password": "pbkdf2_sha256$20000$A6qBFCjkV5yb$Dqm28kbzfimDwMDXChb1Ui/v34Lh0G13pSUs6N139uo=",
      "first_name": "",
      "is_active": true,
      "is_staff": false,
      "is_superuser": false,
      "last_login": "2015-11-29T09:00:26.023Z",
      "user_permissions": [],
      "last_name": "",
      "date_joined": "2015-11-29T08:59:24.468Z",
      "username": "another",
      "email": "another@example.com"
    }
  },
  {
    "pk": 2,
    "model": "sites.site",
    "fields": {
      "domain": "example.com",
      "name": "example.com"
    }
  },
  {
    "pk": 1,
    "model": "account.emailaddress",
    "fields": {
      "primary": true,
      "verified": true,
      "email": "registered@example.com",
      "user": 1
    }
  },
  {
    "pk": 2,
    "model": "account.emailaddress",
    "fields": {
      "primary": true,
      "verified": true,
      "email": "another@example.com",
      "user": 2
    }
  },
  {
    "pk": 1,
    "model": "account.emailconfirmation",
    "fields": {
      "created": "2015-11-29T08:57:57.531Z",
      "sent": "2015-11-29T08:57:58.232Z",
      "email_address": 1,
      "key": "ogntkrdhyk5hstzsikujmffslw5m3fcns5y9xgsndpjcfi6b2pi2vviqfhz50l6n"
    }
  },
  {
    "pk": 2,
    "model": "account.emailconfirmation",
    "fields": {
      "created": "2015-11-29T08:59:24.582Z",
      "sent": "2015-11-29T08:59:24.599Z",
      "email_address": 2,
      "key": "jlcofnrxb1vdnemzbmbh73i7aasiraeixkctc9qbffln493dldowtoacppzrgh31"
    }
  }
]